{
  "title": "Blæsten kommer bragende",
  "videoUrl": "none",
  "author": "Harald H. Lund",
  "music": "Finn Høffding",
  "songVers": [
    [
      "Blæsten kommer bragende,",
      "jip, jap, jagende,",
      "stryger over tagene",
      "og gemmer sig i flagene."
    ],
    [
      "Regnen kommer brusende,",
      "sip, sap, susende,",
      "kurer ned ad husene",
      "og drukner alle musene."
    ],
    [
      "Solen kommer bagende,",
      "solskinsdagene",
      "lægger sig på tagene",
      "og spejler sig i flagene."
    ]
  ],
  "description": "Her finder du teksten til børnesangen, Blæsten kommer bragende.",
  "tags": [
    "sange",
    "børn",
    "dansk"
  ],
  "slug": "blaesten-kommer-bragende",
  "layout": "song",
  "date": 1625672154754
}