{
  "title": "I østen stiger solen op",
  "videoUrl": "https://www.youtube.com/embed/KNwXf_43mqg?rel=0",
  "author": "B. S. Ingemann",
  "music": ": C. E. F. Weyse",
  "songVers": [
    [
      "I østen stiger solen op,",
      "den spreder guld på sky,",
      "går over hav og bjergetop,",
      "går over land og by."
    ],
    [
      "Den kommer fra den favre kyst,",
      "hvor Paradiset lå;",
      "den bringer lys og liv og lyst",
      "til store og til små."
    ],
    [
      "Den hilser os endnu så smukt",
      "fra Edens morgenrød,",
      "hvor træet stod med evig frugt,",
      "hvor livets væld udflød."
    ],
    [
      "Den hilser os fra lysets hjem,",
      "hvor størst Guds lys oprandt",
      "med stjernen over Bethlehem,",
      "som østens vise fandt."
    ],
    [
      "Og med Guds sol udgår fra øst",
      "en himmelsk glans på jord,",
      "et glimt fra Paradisets kyst,",
      "hvor livets abild gror."
    ],
    [
      "Og alle stjerner neje sig,",
      "hvor østens sol går frem,",
      "den synes dem hin stjerne lig,",
      "som stod ved Bethlehem."
    ],
    [
      "Du soles sol fra Bethlehem,",
      "hav tak og lov og pris",
      "for hvert et glimt fra lysets hjem",
      "og fra dit Paradis!"
    ]
  ],
  "description": "Her finder du tekst og melodi til børnesangen, I østen stiger solen op. Klik her.",
  "tags": [
    "sange",
    "børn",
    "dansk"
  ],
  "slug": "i-osten-stiger-solen-op",
  "layout": "song",
  "date": "1.5.2021"
}